{
    "success": true,
    "data": {
        "table": [
            {
                "league_id": "74",
                "season_id": "14",
                "name": "Barcelona",
                "rank": "1",
                "points": "88",
                "matches": "37",
                "goal_diff": "51",
                "goals_scored": "69",
                "goals_conceded": "18",
                "lost": "5",
                "drawn": "4",
                "won": "28",
                "team_id": "21",
                "competition_id": "3",
                "group_id": "1939",
                "group_name": "1",
                "stage_name": "Regular Season",
                "stage_id": "2131"
            },
            {
                "league_id": "74",
                "season_id": "14",
                "name": "Real Madrid",
                "rank": "2",
                "points": "77",
                "matches": "37",
                "goal_diff": "39",
                "goals_scored": "74",
                "goals_conceded": "35",
                "lost": "8",
                "drawn": "5",
                "won": "24",
                "team_id": "27",
                "competition_id": "3",
                "group_id": "1939",
                "group_name": "1",
                "stage_name": "Regular Season",
                "stage_id": "2131"
            },
            {
                "league_id": "74",
                "season_id": "14",
                "name": "Atletico Madrid",
                "rank": "3",
                "points": "76",
                "matches": "37",
                "goal_diff": "37",
                "goals_scored": "68",
                "goals_conceded": "31",
                "lost": "7",
                "drawn": "7",
                "won": "23",
                "team_id": "26",
                "competition_id": "3",
                "group_id": "1939",
                "group_name": "1",
                "stage_name": "Regular Season",
                "stage_id": "2131"
            },
            {
                "league_id": "74",
                "season_id": "14",
                "name": "Real Sociedad",
                "rank": "4",
                "points": "68",
                "matches": "37",
                "goal_diff": "15",
                "goals_scored": "49",
                "goals_conceded": "34",
                "lost": "9",
                "drawn": "8",
                "won": "20",
                "team_id": "22",
                "competition_id": "3",
                "group_id": "1939",
                "group_name": "1",
                "stage_name": "Regular Season",
                "stage_id": "2131"
            },
            {
                "league_id": "74",
                "season_id": "14",
                "name": "Villarreal",
                "rank": "5",
                "points": "63",
                "matches": "37",
                "goal_diff": "19",
                "goals_scored": "57",
                "goals_conceded": "38",
                "lost": "12",
                "drawn": "6",
                "won": "19",
                "team_id": "33",
                "competition_id": "3",
                "group_id": "1939",
                "group_name": "1",
                "stage_name": "Regular Season",
                "stage_id": "2131"
            },
            {
                "league_id": "74",
                "season_id": "14",
                "name": "Real Betis",
                "rank": "6",
                "points": "59",
                "matches": "37",
                "goal_diff": "5",
                "goals_scored": "45",
                "goals_conceded": "40",
                "lost": "12",
                "drawn": "8",
                "won": "17",
                "team_id": "35",
                "competition_id": "3",
                "group_id": "1939",
                "group_name": "1",
                "stage_name": "Regular Season",
                "stage_id": "2131"
            },
            {
                "league_id": "74",
                "season_id": "14",
                "name": "Osasuna",
                "rank": "7",
                "points": "50",
                "matches": "37",
                "goal_diff": "-6",
                "goals_scored": "35",
                "goals_conceded": "41",
                "lost": "15",
                "drawn": "8",
                "won": "14",
                "team_id": "794",
                "competition_id": "3",
                "group_id": "1939",
                "group_name": "1",
                "stage_name": "Regular Season",
                "stage_id": "2131"
            },
            {
                "league_id": "74",
                "season_id": "14",
                "name": "Athletic Bilbao",
                "rank": "8",
                "points": "50",
                "matches": "37",
                "goal_diff": "4",
                "goals_scored": "46",
                "goals_conceded": "42",
                "lost": "15",
                "drawn": "8",
                "won": "14",
                "team_id": "24",
                "competition_id": "3",
                "group_id": "1939",
                "group_name": "1",
                "stage_name": "Regular Season",
                "stage_id": "2131"
            },
            {
                "league_id": "74",
                "season_id": "14",
                "name": "Girona",
                "rank": "9",
                "points": "49",
                "matches": "37",
                "goal_diff": "4",
                "goals_scored": "57",
                "goals_conceded": "53",
                "lost": "14",
                "drawn": "10",
                "won": "13",
                "team_id": "31",
                "competition_id": "3",
                "group_id": "1939",
                "group_name": "1",
                "stage_name": "Regular Season",
                "stage_id": "2131"
            },
            {
                "league_id": "74",
                "season_id": "14",
                "name": "Rayo Vallecano",
                "rank": "10",
                "points": "49",
                "matches": "37",
                "goal_diff": "-5",
                "goals_scored": "45",
                "goals_conceded": "50",
                "lost": "14",
                "drawn": "10",
                "won": "13",
                "team_id": "792",
                "competition_id": "3",
                "group_id": "1939",
                "group_name": "1",
                "stage_name": "Regular Season",
                "stage_id": "2131"
            },
            {
                "league_id": "74",
                "season_id": "14",
                "name": "Sevilla",
                "rank": "11",
                "points": "49",
                "matches": "37",
                "goal_diff": "-6",
                "goals_scored": "46",
                "goals_conceded": "52",
                "lost": "14",
                "drawn": "10",
                "won": "13",
                "team_id": "23",
                "competition_id": "3",
                "group_id": "1939",
                "group_name": "1",
                "stage_name": "Regular Season",
                "stage_id": "2131"
            },
            {
                "league_id": "74",
                "season_id": "14",
                "name": "Mallorca",
                "rank": "12",
                "points": "47",
                "matches": "37",
                "goal_diff": "-9",
                "goals_scored": "34",
                "goals_conceded": "43",
                "lost": "16",
                "drawn": "8",
                "won": "13",
                "team_id": "1814",
                "competition_id": "3",
                "group_id": "1939",
                "group_name": "1",
                "stage_name": "Regular Season",
                "stage_id": "2131"
            },
            {
                "league_id": "74",
                "season_id": "14",
                "name": "Cadiz",
                "rank": "13",
                "points": "41",
                "matches": "37",
                "goal_diff": "-23",
                "goals_scored": "29",
                "goals_conceded": "52",
                "lost": "16",
                "drawn": "11",
                "won": "10",
                "team_id": "798",
                "competition_id": "3",
                "group_id": "1939",
                "group_name": "1",
                "stage_name": "Regular Season",
                "stage_id": "2131"
            },
            {
                "league_id": "74",
                "season_id": "14",
                "name": "Getafe",
                "rank": "14",
                "points": "41",
                "matches": "37",
                "goal_diff": "-11",
                "goals_scored": "34",
                "goals_conceded": "45",
                "lost": "16",
                "drawn": "11",
                "won": "10",
                "team_id": "30",
                "competition_id": "3",
                "group_id": "1939",
                "group_name": "1",
                "stage_name": "Regular Season",
                "stage_id": "2131"
            },
            {
                "league_id": "74",
                "season_id": "14",
                "name": "Valencia",
                "rank": "15",
                "points": "41",
                "matches": "37",
                "goal_diff": "-3",
                "goals_scored": "41",
                "goals_conceded": "44",
                "lost": "18",
                "drawn": "8",
                "won": "11",
                "team_id": "29",
                "competition_id": "3",
                "group_id": "1939",
                "group_name": "1",
                "stage_name": "Regular Season",
                "stage_id": "2131"
            },
            {
                "league_id": "74",
                "season_id": "14",
                "name": "Almeria",
                "rank": "16",
                "points": "40",
                "matches": "37",
                "goal_diff": "-16",
                "goals_scored": "46",
                "goals_conceded": "62",
                "lost": "19",
                "drawn": "7",
                "won": "11",
                "team_id": "287",
                "competition_id": "3",
                "group_id": "1939",
                "group_name": "1",
                "stage_name": "Regular Season",
                "stage_id": "2131"
            },
            {
                "league_id": "74",
                "season_id": "14",
                "name": "Celta Vigo",
                "rank": "17",
                "points": "40",
                "matches": "37",
                "goal_diff": "-11",
                "goals_scored": "41",
                "goals_conceded": "52",
                "lost": "17",
                "drawn": "10",
                "won": "10",
                "team_id": "32",
                "competition_id": "3",
                "group_id": "1939",
                "group_name": "1",
                "stage_name": "Regular Season",
                "stage_id": "2131"
            },
            {
                "league_id": "74",
                "season_id": "14",
                "name": "Valladolid",
                "rank": "18",
                "points": "39",
                "matches": "37",
                "goal_diff": "-30",
                "goals_scored": "33",
                "goals_conceded": "63",
                "lost": "20",
                "drawn": "6",
                "won": "11",
                "team_id": "235",
                "competition_id": "3",
                "group_id": "1939",
                "group_name": "1",
                "stage_name": "Regular Season",
                "stage_id": "2131"
            },
            {
                "league_id": "74",
                "season_id": "14",
                "name": "Espanyol",
                "rank": "19",
                "points": "36",
                "matches": "37",
                "goal_diff": "-17",
                "goals_scored": "49",
                "goals_conceded": "66",
                "lost": "17",
                "drawn": "12",
                "won": "8",
                "team_id": "38",
                "competition_id": "3",
                "group_id": "1939",
                "group_name": "1",
                "stage_name": "Regular Season",
                "stage_id": "2131"
            },
            {
                "league_id": "74",
                "season_id": "14",
                "name": "Elche",
                "rank": "20",
                "points": "24",
                "matches": "37",
                "goal_diff": "-37",
                "goals_scored": "29",
                "goals_conceded": "66",
                "lost": "23",
                "drawn": "9",
                "won": "5",
                "team_id": "1309",
                "competition_id": "3",
                "group_id": "1939",
                "group_name": "1",
                "stage_name": "Regular Season",
                "stage_id": "2131"
            }
        ]
    }
}